poetry_codeartifact/__init__.py
poetry_codeartifact/commands.py
poetry_codeartifact/plugin.py
poetry_codeartifact/py.typed
poetry_codeartifact/settings.py
poetry_codeartifact-0.3.0.dist-info/LICENSE
poetry_codeartifact-0.3.0.dist-info/METADATA
poetry_codeartifact-0.3.0.dist-info/WHEEL
poetry_codeartifact-0.3.0.dist-info/entry_points.txt
poetry_codeartifact-0.3.0.dist-info/RECORD
