Metadata-Version: 2.3
Name: poetry-codeartifact
Version: 0.3.0
Summary: For using AWS CodeArtifact with Poetry.
License: MIT
Author: Micael Jarniac
Author-email: micael@jarniac.dev
Requires-Python: >=3.9,<4.0
Classifier: Development Status :: 1 - Planning
Classifier: License :: OSI Approved :: MIT License
Classifier: Natural Language :: English
Classifier: Operating System :: OS Independent
Classifier: Programming Language :: Python :: 3
Classifier: Programming Language :: Python :: 3.9
Classifier: Programming Language :: Python :: 3.10
Classifier: Programming Language :: Python :: 3.11
Classifier: Programming Language :: Python :: 3.12
Classifier: Programming Language :: Python :: 3.13
Classifier: Typing :: Typed
Requires-Dist: boto3 (>=1.35.85,<2.0.0)
Requires-Dist: loguru (>=0.7.0,<0.8.0)
Requires-Dist: poetry (>=2.0.1,<3.0.0)
Requires-Dist: pydantic (>=2.10.5,<3.0.0)
Requires-Dist: tomli (>=2.2.1,<3.0.0)
Project-URL: Bug Tracker, https://github.com/MicaelJarniac/poetry-codeartifact/issues
Project-URL: Changelog, https://github.com/MicaelJarniac/poetry-codeartifact/blob/main/docs/CHANGELOG.md
Project-URL: Documentation, https://poetry-codeartifact.readthedocs.io
Project-URL: Homepage, https://github.com/MicaelJarniac/poetry-codeartifact
Project-URL: Repository, https://github.com/MicaelJarniac/poetry-codeartifact
